{
  "db_name": "PostgreSQL",
  "query": "\n\t\t\t\tINSERT INTO v1_task_result (payload, job_id, backend_name, result)\n\t\t\t\tVALUES ($1, $2, $3, $4)\n\t\t\t\tRETURNING id\n\t\t\t\t",
  "describe": {
    "columns": [
      {
        "ordinal": 0,
        "name": "id",
        "type_info": "Int4"
      }
    ],
    "parameters": {
      "Left": [
        "Jsonb",
        "Int4",
        "Text",
        "Jsonb"
      ]
    },
    "nullable": [
      false
    ]
  },
  "hash": "aaa1cf5961de24b1fb68f856205afe4d3bfaf55e3371f46a472ea3d5705d35b2"
}
